biscuit_entities/__init__.py
biscuit_entities/entity.py
biscuit_entities/property.py
biscuit_entities/singleton.py
biscuit_entities-0.0.1.dist-info/METADATA
biscuit_entities-0.0.1.dist-info/WHEEL
biscuit_entities-0.0.1.dist-info/top_level.txt
biscuit_entities-0.0.1.dist-info/RECORD
